[{"idTitulo":"2059","id_libro":"19","capitulo":"122","versiculo":"1","titulo":"C\u00e1ntico para los peregrinos que suben a adorar a Yo Soy en YaHrushalem (Jerusal\u00e9n).\u00a0"},{"idTitulo":"2060","id_libro":"19","capitulo":"122","versiculo":"1","titulo":"(C\u00e1ntico para los peregrinos, de ascenso gradual. Salmo de David)."},{"id_libro":"19","capitulo":"122","versiculo":"1","texto":"Yo me gozo con los que me dicen: Subamos a la Casa de Yo Soy y ador\u00e9mosle."},{"id_libro":"19","capitulo":"122","versiculo":"2","texto":"Ciudad de Jerusal\u00e9n, \u00a1Hemos llegado a la Puerta! \u00a1 \u00a1Ya estamos dentro de tus muros!"},{"id_libro":"19","capitulo":"122","versiculo":"3","texto":"Oh Nueva YaHrushalem (Jerusal\u00e9n), la Ciudad que fue edificada armoniosamente para la Unidad;"},{"id_libro":"19","capitulo":"122","versiculo":"4","texto":"\u00a1Hasta Ti Yo Soy (YH) llegan todas las tribus de Israel! \u00a1Hasta Ti llega Tu pueblo para adorar Tu Nombre, tal como Yo Soy Lo orden\u00f3!"},{"id_libro":"19","capitulo":"122","versiculo":"5","texto":"Porque all\u00ed se establecieron los tribunales para juicio; El trono del Hijo de David."},{"id_libro":"19","capitulo":"122","versiculo":"6","texto":"Pidan por la paz de YaHrushalem (Jerusal\u00e9n);   Sean prosperados los que Te aman."},{"id_libro":"19","capitulo":"122","versiculo":"7","texto":"Sea la paz dentro de tus muros; Y el reposo dentro de Tus palacios."},{"id_libro":"19","capitulo":"122","versiculo":"8","texto":"Por amor de mis hermanos y mis amigos Dir\u00e9 yo: Que haya perd\u00f3n en ti YaHrushalem (Jerusal\u00e9n)."},{"id_libro":"19","capitulo":"122","versiculo":"9","texto":"Por amor a la Casa de Yo Soy nuestro Dios; Interceder\u00e9 por tu bendici\u00f3n."}]